Modified_Thompson_Tau_Test/__init__.py
Modified_Thompson_Tau_Test/modified_thompson_tau_test.py
modified_thompson_tau_test-0.1.3.dist-info/LICENSE
modified_thompson_tau_test-0.1.3.dist-info/METADATA
modified_thompson_tau_test-0.1.3.dist-info/WHEEL
modified_thompson_tau_test-0.1.3.dist-info/top_level.txt
modified_thompson_tau_test-0.1.3.dist-info/RECORD
