Metadata-Version: 2.1
Name: modified-thompson-tau-test
Version: 0.1.3
Summary: Implementation of Modified Thompson Tau Test in Python
Home-page: https://github.com/vvaezian/modified_thompson_tau_test
Author: Vahid Vaezian
Author-email: vahid.vaezian@gmail.com
Classifier: Programming Language :: Python :: 3
Classifier: License :: OSI Approved :: MIT License
Classifier: Operating System :: OS Independent
License-File: LICENSE
Requires-Dist: pandas
